[
    {
        "id": 1,
        "product_id": 1,
        "name": "Free",
        "limit_btc_diary": 0.005000000000000000,
        "limit_brl_diary": 99.000000000000000000,
        "limit_usd_diary": 29.000000000000000000,
        "limit_transaction_auto": 0.005000000000000000,
        "brokerage_fee": 4.000,
        "is_referrable": 0,
        "referral_profit": 0.000,
        "is_gateway_elegible": 0,
        "gateway_tax": 0.000,
        "is_gateway_mmn_elegible": 0,
        "gateway_mmn_tax": 0.000,
        "is_card_elegible": 0,
        "is_active": 1,
        "created_at": "2018\/12\/20 01:18:06",
        "updated_at": "2019\/1\/28 19:36:41"
    },
    {
        "id": 2,
        "product_id": 2,
        "name": "Basic",
        "limit_btc_diary": 0.010000000000000000,
        "limit_brl_diary": 999.000000000000000000,
        "limit_usd_diary": 249.000000000000000000,
        "limit_transaction_auto": 0.001000000000000000,
        "brokerage_fee": 3.000,
        "is_referrable": 0,
        "referral_profit": 0.000,
        "is_gateway_elegible": 0,
        "gateway_tax": 0.000,
        "is_gateway_mmn_elegible": 1,
        "gateway_mmn_tax": 0.000,
        "is_card_elegible": 0,
        "is_active": 1,
        "created_at": "2018\/12\/20 01:18:06",
        "updated_at": "2018\/12\/20 01:18:06"
    },
    {
        "id": 3,
        "product_id": 3,
        "name": "Pro",
        "limit_btc_diary": 1.000000000000000000,
        "limit_brl_diary": 9999.000000000000000000,
        "limit_usd_diary": 2499.000000000000000000,
        "limit_transaction_auto": 0.050000000000000000,
        "brokerage_fee": 2.000,
        "is_referrable": 0,
        "referral_profit": 0.000,
        "is_gateway_elegible": 1,
        "gateway_tax": 10.000,
        "is_gateway_mmn_elegible": 0,
        "gateway_mmn_tax": 0.000,
        "is_card_elegible": 0,
        "is_active": 1,
        "created_at": "2018\/12\/20 01:18:06",
        "updated_at": "2018\/12\/20 01:18:06"
    },
    {
        "id": 4,
        "product_id": 4,
        "name": "Gold",
        "limit_btc_diary": 5.000000000000000000,
        "limit_brl_diary": 24990.000000000000000000,
        "limit_usd_diary": 8300.000000000000000000,
        "limit_transaction_auto": 0.050000000000000000,
        "brokerage_fee": 1.000,
        "is_referrable": 0,
        "referral_profit": 0.000,
        "is_gateway_elegible": 1,
        "gateway_tax": 0.000,
        "is_gateway_mmn_elegible": 1,
        "gateway_mmn_tax": 0.000,
        "is_card_elegible": 0,
        "is_active": 1,
        "created_at": "2018\/12\/20 01:18:06",
        "updated_at": "2018\/12\/20 01:18:06"
    }
]
